evernote2/__init__.py
evernote2/__version__.py
evernote2-1.9.1.dist-info/LICENSE
evernote2-1.9.1.dist-info/METADATA
evernote2-1.9.1.dist-info/NOTICE
evernote2-1.9.1.dist-info/WHEEL
evernote2-1.9.1.dist-info/top_level.txt
evernote2-1.9.1.dist-info/RECORD
