Metadata-Version: 2.1
Name: evernote2
Version: 1.9.1
Summary: another Evernote SDK for Python
Home-page: https://github.com/JackonYang/evernote-sdk-python
Author: Jackon Yang
Author-email: i@jackon.me
License: BSD
Platform: UNKNOWN
Requires-Dist: thrift
Requires-Dist: oauth2
